ufo/__init__.py
ufo/containers.py
ufo/scope.py
ufo/wrappers.py
ufo_tools-0.3.0.dist-info/METADATA
ufo_tools-0.3.0.dist-info/WHEEL
ufo_tools-0.3.0.dist-info/licenses/LICENSE
ufo_tools-0.3.0.dist-info/RECORD
