Metadata-Version: 2.1
Name: ufo_tools
Version: 0.3.0
Summary: And unintrusive functional offering of tools
Project-URL: Repository, https://github.com/benrutter/monads
Project-URL: Documentation, https://benrutter.github.io/monads/monadcontainers.html
Project-URL: Homepage, https://benrutter.github.io/monads/monadcontainers.html
Project-URL: Issues, https://github.com/benrutter/monads/issues
License-File: LICENSE
Classifier: Development Status :: 3 - Alpha
Classifier: Intended Audience :: Developers
Classifier: Programming Language :: Python :: 3.9
Classifier: Programming Language :: Python :: 3.10
Classifier: Programming Language :: Python :: 3.11
Classifier: Programming Language :: Python :: 3.12
Requires-Python: >=3.8
